DESCRIPTION
LICENSE
MANIFEST.in
README
README.rst
setup.py
async_tasks/__init__.py
async_tasks/redisqueue.py
async_tasks/settings.py
async_tasks/tests.py
async_tasks/utils.py
async_tasks/management/__init__.py
async_tasks/management/__init__.pyc
async_tasks/management/commands/__init__.py
async_tasks/management/commands/__init__.pyc
async_tasks/management/commands/django_async_tasks.py
async_tasks/management/commands/django_async_tasks.pyc
django_async_tasks.egg-info/PKG-INFO
django_async_tasks.egg-info/SOURCES.txt
django_async_tasks.egg-info/dependency_links.txt
django_async_tasks.egg-info/requires.txt
django_async_tasks.egg-info/top_level.txt