Metadata-Version: 1.1
Name: django-async-tasks
Version: 0.1.1
Summary: Django application. It's a simple system to process queue task in real time.
Home-page: https://github.com/ivansurov/django-async-tasks
Author: Ivan Surov
Author-email: ivansurovv@gmail.com
License: GNU General Public License (GPL)
Keywords: task queue,job queue,async tasks,redis,python,django
Platform: UNKNOWN
Classifier: Environment :: Web Environment
Classifier: Framework :: Django
Classifier: Intended Audience :: Developers
Classifier: License :: OSI Approved :: GNU General Public License (GPL)
Classifier: Operating System :: OS Independent
Classifier: Programming Language :: Python
Classifier: Programming Language :: Python :: 2.6
Classifier: Programming Language :: Python :: 2.7
Classifier: Topic :: Internet :: WWW/HTTP :: Dynamic Content
